Utubes/__init__.py
Utubes/exception/__init__.py
Utubes/exception/exception.py
Utubes/functions/__init__.py
Utubes/functions/collections.py
Utubes/functions/function01.py
Utubes/functions/function02.py
Utubes/functions/function03.py
Utubes/functions/function04.py
Utubes/functions/function05.py
Utubes/functions/function06.py
Utubes/functions/function07.py
Utubes/functions/function08.py
Utubes/functions/function09.py
Utubes/functions/function10.py
Utubes/functions/function13.py
Utubes/functions/function14.py
Utubes/functions/function15.py
Utubes/scripts/__init__.py
Utubes/scripts/script01.py
Utubes/scripts/script02.py
Utubes/scripts/script03.py
Utubes/scripts/script04.py
Utubes/scripts/script05.py
utubes-0.0.62.dist-info/METADATA
utubes-0.0.62.dist-info/WHEEL
utubes-0.0.62.dist-info/top_level.txt
utubes-0.0.62.dist-info/RECORD
